immutable_defaults-0.1.3.dist-info/METADATA
immutable_defaults-0.1.3.dist-info/WHEEL
immutable_defaults-0.1.3.dist-info/licenses/LICENSE
immutable_defaults/__init__.py
immutable_defaults/immutable_defaults.py
immutable_defaults-0.1.3.dist-info/RECORD
