Metadata-Version: 2.1
Name: immutable-defaults
Version: 0.1.3
Summary: Immutable defaults for Python
Author-Email: clvnkhr <calvin_khor@hotmail.com>
License: MIT
Requires-Python: >=3.12
